<mediaCollection>
    <collectionName>Media Collection</collectionName>
    <ip>176.58.60.57:8000/data</ip>
</mediaCollection>
<mediaBase>
    <baseName>AppScreen</baseName>
    <baseType>1</baseType>
    <path>AppScreen</path>
    <extensions>
        <ext>jpg</ext>
    </extensions>
    <extensions>
        <ext>mp4</ext>
    </extensions>
    <file>
        <name>01.jpg</name>
        <path>AppScreen</path>
        <prevName>01.jpg</prevName>
        <prevPath>prev</prevPath>
        <bType>1</bType>
        <type>4</type>
        <ar>2</ar>
        <w>1824</w>
        <h>2736</h>
        <time>0.000000000</time>
    </file>
    <file>
        <name>02.jpg</name>
        <path>AppScreen</path>
        <prevName>02.jpg</prevName>
        <prevPath>prev</prevPath>
        <bType>1</bType>
        <type>4</type>
        <ar>2</ar>
        <w>1824</w>
        <h>2736</h>
        <time>0.000000000</time>
    </file>
    <file>
        <name>03.jpg</name>
        <path>AppScreen</path>
        <prevName>03.jpg</prevName>
        <prevPath>prev</prevPath>
        <bType>1</bType>
        <type>4</type>
        <ar>2</ar>
        <w>1824</w>
        <h>2736</h>
        <time>0.000000000</time>
    </file>
</mediaBase>
<mediaBase>
    <baseName>Music</baseName>
    <baseType>2</baseType>
    <path>Music</path>
    <extensions>
        <ext>mp3</ext>
    </extensions>
    <file>
        <name>01.mp3</name>
        <path>Music</path>
        <prevName>01.mp3</prevName>
        <prevPath>prev</prevPath>
        <bType>2</bType>
        <type>3</type>
        <ar>0</ar>
        <w>0</w>
        <h>0</h>
        <time>118.632003784</time>
    </file>
    <file>
        <name>02.mp3</name>
        <path>Music</path>
        <prevName>02.mp3</prevName>
        <prevPath>prev</prevPath>
        <bType>2</bType>
        <type>3</type>
        <ar>0</ar>
        <w>0</w>
        <h>0</h>
        <time>187.506912231</time>
    </file>
    <file>
        <name>03.mp3</name>
        <path>Music</path>
        <prevName>03.mp3</prevName>
        <prevPath>prev</prevPath>
        <bType>2</bType>
        <type>3</type>
        <ar>0</ar>
        <w>0</w>
        <h>0</h>
        <time>185.808944702</time>
    </file>
    <file>
        <name>04.mp3</name>
        <path>Music</path>
        <prevName>04.mp3</prevName>
        <prevPath>prev</prevPath>
        <bType>2</bType>
        <type>3</type>
        <ar>0</ar>
        <w>0</w>
        <h>0</h>
        <time>126.066932678</time>
    </file>
    <file>
        <name>06.mp3</name>
        <path>Music</path>
        <prevName>06.mp3</prevName>
        <prevPath>prev</prevPath>
        <bType>2</bType>
        <type>3</type>
        <ar>0</ar>
        <w>0</w>
        <h>0</h>
        <time>307.749176025</time>
    </file>
    <file>
        <name>07.mp3</name>
        <path>Music</path>
        <prevName>07.mp3</prevName>
        <prevPath>prev</prevPath>
        <bType>2</bType>
        <type>3</type>
        <ar>0</ar>
        <w>0</w>
        <h>0</h>
        <time>42.475101471</time>
    </file>
</mediaBase>
<mediaBase>
    <baseName>PhotoBackground</baseName>
    <baseType>3</baseType>
    <path>PhotoBackground</path>
    <extensions>
        <ext>jpg</ext>
    </extensions>
</mediaBase>
<mediaBase>
    <baseName>PhotoOverlay</baseName>
    <baseType>4</baseType>
    <path>PhotoOverlay</path>
    <extensions>
        <ext>png</ext>
    </extensions>
</mediaBase>
<mediaBase>
    <baseName>VideoBackground</baseName>
    <baseType>5</baseType>
    <path>VideoBackground</path>
    <extensions>
        <ext>jpg</ext>
    </extensions>
    <extensions>
        <ext>mp4</ext>
    </extensions>
</mediaBase>
<mediaBase>
    <baseName>VideoOverlay</baseName>
    <baseType>6</baseType>
    <path>VideoOverlay</path>
    <extensions>
        <ext>png</ext>
    </extensions>
    <extensions>
        <ext>mov</ext>
    </extensions>
    <file>
        <name>flowers.png</name>
        <path>VideoOverlay</path>
        <prevName>flowers.jpg</prevName>
        <prevPath>prev</prevPath>
        <bType>6</bType>
        <type>6</type>
        <ar>1</ar>
        <w>1920</w>
        <h>1080</h>
        <time>0.000000000</time>
    </file>
    <file>
        <name>flowers1.png</name>
        <path>VideoOverlay</path>
        <prevName>flowers1.jpg</prevName>
        <prevPath>prev</prevPath>
        <bType>6</bType>
        <type>6</type>
        <ar>1</ar>
        <w>1920</w>
        <h>1080</h>
        <time>0.000000000</time>
    </file>
    <file>
        <name>flowers2.png</name>
        <path>VideoOverlay</path>
        <prevName>flowers2.jpg</prevName>
        <prevPath>prev</prevPath>
        <bType>6</bType>
        <type>6</type>
        <ar>1</ar>
        <w>1920</w>
        <h>1080</h>
        <time>0.000000000</time>
    </file>
    <file>
        <name>Flowers3.png</name>
        <path>VideoOverlay</path>
        <prevName>Flowers3.jpg</prevName>
        <prevPath>prev</prevPath>
        <bType>6</bType>
        <type>6</type>
        <ar>3</ar>
        <w>1080</w>
        <h>1080</h>
        <time>0.000000000</time>
    </file>
    <file>
        <name>Flowers4.png</name>
        <path>VideoOverlay</path>
        <prevName>Flowers4.jpg</prevName>
        <prevPath>prev</prevPath>
        <bType>6</bType>
        <type>6</type>
        <ar>1</ar>
        <w>1920</w>
        <h>1080</h>
        <time>0.000000000</time>
    </file>
    <file>
        <name>gold.png</name>
        <path>VideoOverlay</path>
        <prevName>gold.jpg</prevName>
        <prevPath>prev</prevPath>
        <bType>6</bType>
        <type>6</type>
        <ar>1</ar>
        <w>1920</w>
        <h>1080</h>
        <time>0.000000000</time>
    </file>
    <file>
        <name>Graduation.png</name>
        <path>VideoOverlay</path>
        <prevName>Graduation.jpg</prevName>
        <prevPath>prev</prevPath>
        <bType>6</bType>
        <type>6</type>
        <ar>3</ar>
        <w>2500</w>
        <h>2500</h>
        <time>0.000000000</time>
    </file>
    <file>
        <name>HappyBirthday.png</name>
        <path>VideoOverlay</path>
        <prevName>HappyBirthday.jpg</prevName>
        <prevPath>prev</prevPath>
        <bType>6</bType>
        <type>6</type>
        <ar>3</ar>
        <w>1080</w>
        <h>1080</h>
        <time>0.000000000</time>
    </file>
    <file>
        <name>HappyBirthday2.png</name>
        <path>VideoOverlay</path>
        <prevName>HappyBirthday2.jpg</prevName>
        <prevPath>prev</prevPath>
        <bType>6</bType>
        <type>6</type>
        <ar>3</ar>
        <w>1080</w>
        <h>1080</h>
        <time>0.000000000</time>
    </file>
    <file>
        <name>Hearts.png</name>
        <path>VideoOverlay</path>
        <prevName>Hearts.jpg</prevName>
        <prevPath>prev</prevPath>
        <bType>6</bType>
        <type>6</type>
        <ar>1</ar>
        <w>1920</w>
        <h>1080</h>
        <time>0.000000000</time>
    </file>
    <file>
        <name>Hearts2.png</name>
        <path>VideoOverlay</path>
        <prevName>Hearts2.jpg</prevName>
        <prevPath>prev</prevPath>
        <bType>6</bType>
        <type>6</type>
        <ar>1</ar>
        <w>4092</w>
        <h>2893</h>
        <time>0.000000000</time>
    </file>
    <file>
        <name>Hearts3.png</name>
        <path>VideoOverlay</path>
        <prevName>Hearts3.jpg</prevName>
        <prevPath>prev</prevPath>
        <bType>6</bType>
        <type>6</type>
        <ar>1</ar>
        <w>2800</w>
        <h>2000</h>
        <time>0.000000000</time>
    </file>
    <file>
        <name>Like.png</name>
        <path>VideoOverlay</path>
        <prevName>Like.jpg</prevName>
        <prevPath>prev</prevPath>
        <bType>6</bType>
        <type>6</type>
        <ar>3</ar>
        <w>2500</w>
        <h>2500</h>
        <time>0.000000000</time>
    </file>
    <file>
        <name>Post.png</name>
        <path>VideoOverlay</path>
        <prevName>Post.jpg</prevName>
        <prevPath>prev</prevPath>
        <bType>6</bType>
        <type>6</type>
        <ar>3</ar>
        <w>2500</w>
        <h>2500</h>
        <time>0.000000000</time>
    </file>
    <file>
        <name>Post2.png</name>
        <path>VideoOverlay</path>
        <prevName>Post2.jpg</prevName>
        <prevPath>prev</prevPath>
        <bType>6</bType>
        <type>6</type>
        <ar>3</ar>
        <w>1080</w>
        <h>1080</h>
        <time>0.000000000</time>
    </file>
    <file>
        <name>tropic.png</name>
        <path>VideoOverlay</path>
        <prevName>tropic.jpg</prevName>
        <prevPath>prev</prevPath>
        <bType>6</bType>
        <type>6</type>
        <ar>1</ar>
        <w>1920</w>
        <h>1080</h>
        <time>0.000000000</time>
    </file>
    <file>
        <name>tropic2.png</name>
        <path>VideoOverlay</path>
        <prevName>tropic2.jpg</prevName>
        <prevPath>prev</prevPath>
        <bType>6</bType>
        <type>6</type>
        <ar>1</ar>
        <w>1920</w>
        <h>1080</h>
        <time>0.000000000</time>
    </file>
    <file>
        <name>tropic3.png</name>
        <path>VideoOverlay</path>
        <prevName>tropic3.jpg</prevName>
        <prevPath>prev</prevPath>
        <bType>6</bType>
        <type>6</type>
        <ar>1</ar>
        <w>1920</w>
        <h>1080</h>
        <time>0.000000000</time>
    </file>
    <file>
        <name>tropic4.png</name>
        <path>VideoOverlay</path>
        <prevName>tropic4.jpg</prevName>
        <prevPath>prev</prevPath>
        <bType>6</bType>
        <type>6</type>
        <ar>1</ar>
        <w>1920</w>
        <h>1080</h>
        <time>0.000000000</time>
    </file>
    <file>
        <name>tropic5.png</name>
        <path>VideoOverlay</path>
        <prevName>tropic5.jpg</prevName>
        <prevPath>prev</prevPath>
        <bType>6</bType>
        <type>6</type>
        <ar>1</ar>
        <w>1920</w>
        <h>1080</h>
        <time>0.000000000</time>
    </file>
    <file>
        <name>tropic6.png</name>
        <path>VideoOverlay</path>
        <prevName>tropic6.jpg</prevName>
        <prevPath>prev</prevPath>
        <bType>6</bType>
        <type>6</type>
        <ar>1</ar>
        <w>1920</w>
        <h>1080</h>
        <time>0.000000000</time>
    </file>
    <file>
        <name>tropic7.png</name>
        <path>VideoOverlay</path>
        <prevName>tropic7.jpg</prevName>
        <prevPath>prev</prevPath>
        <bType>6</bType>
        <type>6</type>
        <ar>1</ar>
        <w>1920</w>
        <h>1080</h>
        <time>0.000000000</time>
    </file>
    <file>
        <name>tropic8.png</name>
        <path>VideoOverlay</path>
        <prevName>tropic8.jpg</prevName>
        <prevPath>prev</prevPath>
        <bType>6</bType>
        <type>6</type>
        <ar>1</ar>
        <w>1920</w>
        <h>1080</h>
        <time>0.000000000</time>
    </file>
    <file>
        <name>tropic9.png</name>
        <path>VideoOverlay</path>
        <prevName>tropic9.jpg</prevName>
        <prevPath>prev</prevPath>
        <bType>6</bType>
        <type>6</type>
        <ar>1</ar>
        <w>1920</w>
        <h>1080</h>
        <time>0.000000000</time>
    </file>
</mediaBase>
